{"file": "/hci/chaoran_data/android-12.0.0_r31/frameworks/base/libs/hwui/jni/PathEffect.cpp", "jni_methods": [{"java_fun": "nativeDestructor", "java_sig": "(J)V", "cpp_fun": "destructor", "java_fun_full": "android.graphics.PathEffect void nativeDestructor(long)"}, {"java_fun": "nativeCreate", "java_sig": "(JJ)J", "cpp_fun": "Compose_constructor", "java_fun_full": "android.graphics.ComposePathEffect long nativeCreate(long, long)"}, {"java_fun": "nativeCreate", "java_sig": "(JJ)J", "cpp_fun": "Sum_constructor", "java_fun_full": "android.graphics.SumPathEffect long nativeCreate(long, long)"}, {"java_fun": "nativeCreate", "java_sig": "([FF)J", "cpp_fun": "Dash_constructor", "java_fun_full": "android.graphics.DashPathEffect long nativeCreate(float[], float)"}, {"java_fun": "nativeCreate", "java_sig": "(JFFI)J", "cpp_fun": "OneD_constructor", "java_fun_full": "android.graphics.PathDashPathEffect long nativeCreate(long, float, float, int)"}, {"java_fun": "nativeCreate", "java_sig": "(F)J", "cpp_fun": "Corner_constructor", "java_fun_full": "android.graphics.CornerPathEffect long nativeCreate(float)"}, {"java_fun": "nativeCreate", "java_sig": "(FF)J", "cpp_fun": "Discrete_constructor", "java_fun_full": "android.graphics.DiscretePathEffect long nativeCreate(float, float)"}], "dependency": []}