{"file": "/hci/chaoran_data/android-12.0.0_r31/frameworks/base/core/jni/android_os_PerformanceHintManager.cpp", "jni_methods": [{"java_fun": "nativeAcquireManager", "java_sig": "()J", "cpp_fun": "nativeAcquireManager", "java_fun_full": "android.os.PerformanceHintManager long nativeAcquireManager()"}, {"java_fun": "nativeGetPreferredUpdateRateNanos", "java_sig": "(J)J", "cpp_fun": "nativeGetPreferredUpdateRateNanos", "java_fun_full": "android.os.PerformanceHintManager long nativeGetPreferredUpdateRateNanos(long)"}, {"java_fun": "nativeCreateSession", "java_sig": "(J[IJ)J", "cpp_fun": "nativeCreateSession", "java_fun_full": "android.os.PerformanceHintManager long nativeCreateSession(long, int[], long)"}, {"java_fun": "nativeUpdateTargetWorkDuration", "java_sig": "(JJ)V", "cpp_fun": "nativeUpdateTargetWorkDuration", "java_fun_full": "android.os.PerformanceHintManager void nativeUpdateTargetWorkDuration(long, long)"}, {"java_fun": "nativeReportActualWorkDuration", "java_sig": "(JJ)V", "cpp_fun": "nativeReportActualWorkDuration", "java_fun_full": "android.os.PerformanceHintManager void nativeReportActualWorkDuration(long, long)"}, {"java_fun": "nativeCloseSession", "java_sig": "(J)V", "cpp_fun": "nativeCloseSession", "java_fun_full": "android.os.PerformanceHintManager void nativeCloseSession(long)"}], "dependency": [["android::nativeAcquireManager(JNIEnv *, jclass)", "android::::ensureAPerformanceHintBindingInitialized()"], ["android::nativeGetPreferredUpdateRateNanos(JNIEnv *, jclass, jlong)", "android::::ensureAPerformanceHintBindingInitialized()"], ["android::nativeCreateSession(JNIEnv *, jclass, jlong, jintArray, jlong)", "android::::ensureAPerformanceHintBindingInitialized()"], ["android::nativeUpdateTargetWorkDuration(JNIEnv *, jclass, jlong, jlong)", "android::::ensureAPerformanceHintBindingInitialized()"], ["android::nativeReportActualWorkDuration(JNIEnv *, jclass, jlong, jlong)", "android::::ensureAPerformanceHintBindingInitialized()"], ["android::nativeCloseSession(JNIEnv *, jclass, jlong)", "android::::ensureAPerformanceHintBindingInitialized()"]]}